pg_edr/__init__.py
pg_edr/edr.py
pg_edr/lib.py
pgedr-0.1.0.dist-info/licenses/LICENSE
pgedr-0.1.0.dist-info/METADATA
pgedr-0.1.0.dist-info/WHEEL
pgedr-0.1.0.dist-info/top_level.txt
pgedr-0.1.0.dist-info/RECORD
