Metadata-Version: 2.4
Name: pgedr
Version: 0.1.0
Summary: An OGC API EDR implementation using SQL for pygeoapi
Author-email: Benjamin Webb <bwebb@lincolninst.edu>
License: MIT License
Project-URL: Homepage, https://github.com/internetofwater/pgedr
Project-URL: Repository, https://github.com/internetofwater/pgedr
Keywords: pygeoapi,edr,data
Classifier: Development Status :: 4 - Beta
Classifier: Environment :: Console
Classifier: Intended Audience :: Developers
Classifier: Intended Audience :: Science/Research
Classifier: License :: OSI Approved :: MIT License
Classifier: Operating System :: OS Independent
Classifier: Programming Language :: Python
Classifier: Topic :: Scientific/Engineering :: Atmospheric Science
Classifier: Topic :: Scientific/Engineering :: GIS
Classifier: Topic :: Scientific/Engineering :: Information Analysis
Requires-Python: >=3.10
License-File: LICENSE
Requires-Dist: cryptography>=44.0.3
Requires-Dist: geoalchemy2
Requires-Dist: psycopg2
Requires-Dist: pydantic
Requires-Dist: pygeoapi>=0.21.0
Requires-Dist: pymysql>=1.1.1
Requires-Dist: pytest
Requires-Dist: pytest-cov
Dynamic: license-file
